MANIFEST.in
NEWS.txt
README.rst
setup.cfg
setup.py
src/iscool_e/__init__.py
src/iscool_e.pynba.egg-info/PKG-INFO
src/iscool_e.pynba.egg-info/SOURCES.txt
src/iscool_e.pynba.egg-info/dependency_links.txt
src/iscool_e.pynba.egg-info/namespace_packages.txt
src/iscool_e.pynba.egg-info/not-zip-safe
src/iscool_e.pynba.egg-info/requires.txt
src/iscool_e.pynba.egg-info/top_level.txt
src/iscool_e/pynba/__init__.py
src/iscool_e/pynba/collector.py
src/iscool_e/pynba/ctx.py
src/iscool_e/pynba/globals.py
src/iscool_e/pynba/local.py
src/iscool_e/pynba/log.py
src/iscool_e/pynba/message.py
src/iscool_e/pynba/middleware.py
src/iscool_e/pynba/reporter.py
src/iscool_e/pynba/util.py